COPYING
MANIFEST.in
README.md
setup.py
rds_snapshot/__init__.py
rds_snapshot.egg-info/PKG-INFO
rds_snapshot.egg-info/SOURCES.txt
rds_snapshot.egg-info/dependency_links.txt
rds_snapshot.egg-info/entry_points.txt
rds_snapshot.egg-info/requires.txt
rds_snapshot.egg-info/top_level.txt